[
  {
    "legal_name": "Randles Electric Service Co Inc",
    "dba_name": null,
    "address": "2216 Moneda St",
    "city": "Haltom City",
    "county": "Tarrant",
    "state": "TX",
    "zip": "76117",
    "phone": "8178319593",
    "website": null,
    "naics_code": "238210",
    "license_number": "17451",
    "license_type": "Electrical Contractor",
    "license_subtype": "EC",
    "license_status": "Active",
    "license_holder_name": "Randles Electric Service Co Inc",
    "license_expiration_date": "07/23/2026",
    "license_issue_year_estimate": 2004,
    "data_sources": [
      {
        "source": "TDLR Electrical Contractor bulk CSV",
        "url": "https://www.tdlr.texas.gov/dbproduction2/Lteecele.csv",
        "fetched_at": "2026-05-16T04:51:42.671065Z",
        "fields": [
          "legal_name",
          "license_number",
          "license_type",
          "license_holder_name",
          "address",
          "city",
          "county",
          "state",
          "zip",
          "phone",
          "license_expiration_date"
        ]
      }
    ],
    "verification_notes": "Sourced from TDLR Electrical Contractor active license roster \u2014 real, currently-operating TX Electrical Contractor license. License number used as tenure proxy.",
    "domain_candidates": [
      "randleselectric.com",
      "randleselectrical.com",
      "randleselectricservices.com",
      "randleselectricserviceco.com"
    ],
    "enrichment_status": "spine_only",
    "enrichment": null
  },
  {
    "legal_name": "Ace Electric",
    "dba_name": null,
    "address": "John Payne, 538 Gordy",
    "city": "Bacliff",
    "county": "Galveston",
    "state": "TX",
    "zip": "77518",
    "phone": "2812369327",
    "website": null,
    "naics_code": "238210",
    "license_number": "17453",
    "license_type": "Electrical Contractor",
    "license_subtype": "EC",
    "license_status": "Active",
    "license_holder_name": "Ace Electric",
    "license_expiration_date": "08/26/2026",
    "license_issue_year_estimate": 2004,
    "data_sources": [
      {
        "source": "TDLR Electrical Contractor bulk CSV",
        "url": "https://www.tdlr.texas.gov/dbproduction2/Lteecele.csv",
        "fetched_at": "2026-05-16T04:51:42.671068Z",
        "fields": [
          "legal_name",
          "license_number",
          "license_type",
          "license_holder_name",
          "address",
          "city",
          "county",
          "state",
          "zip",
          "phone",
          "license_expiration_date"
        ]
      }
    ],
    "verification_notes": "Sourced from TDLR Electrical Contractor active license roster \u2014 real, currently-operating TX Electrical Contractor license. License number used as tenure proxy.",
    "domain_candidates": [
      "aceelectric.com",
      "aceelectrical.com",
      "aceelectricservices.com"
    ],
    "enrichment_status": "spine_only",
    "enrichment": null
  },
  {
    "legal_name": "Cotton Electric Service Inc",
    "dba_name": null,
    "address": "1130 S Cedar Ridge Rd",
    "city": "Duncanville",
    "county": "Dallas",
    "state": "TX",
    "zip": "75137",
    "phone": "9722964020",
    "website": null,
    "naics_code": "238210",
    "license_number": "17462",
    "license_type": "Electrical Contractor",
    "license_subtype": "EC",
    "license_status": "Active",
    "license_holder_name": "Cotton Electric Service Inc",
    "license_expiration_date": "07/30/2026",
    "license_issue_year_estimate": 2004,
    "data_sources": [
      {
        "source": "TDLR Electrical Contractor bulk CSV",
        "url": "https://www.tdlr.texas.gov/dbproduction2/Lteecele.csv",
        "fetched_at": "2026-05-16T04:51:42.671070Z",
        "fields": [
          "legal_name",
          "license_number",
          "license_type",
          "license_holder_name",
          "address",
          "city",
          "county",
          "state",
          "zip",
          "phone",
          "license_expiration_date"
        ]
      }
    ],
    "verification_notes": "Sourced from TDLR Electrical Contractor active license roster \u2014 real, currently-operating TX Electrical Contractor license. License number used as tenure proxy.",
    "domain_candidates": [
      "cottonelectric.com",
      "cottonelectrical.com",
      "cottonelectricservices.com",
      "cottonelectricservice.com"
    ],
    "enrichment_status": "spine_only",
    "enrichment": null
  },
  {
    "legal_name": "Bewley Electric",
    "dba_name": null,
    "address": "717 N Chestnut St",
    "city": "Mckinney",
    "county": "Collin",
    "state": "TX",
    "zip": "75069",
    "phone": "9727547884",
    "website": null,
    "naics_code": "238210",
    "license_number": "17465",
    "license_type": "Electrical Contractor",
    "license_subtype": "EC",
    "license_status": "Active",
    "license_holder_name": "Bewley Electric",
    "license_expiration_date": "07/23/2026",
    "license_issue_year_estimate": 2004,
    "data_sources": [
      {
        "source": "TDLR Electrical Contractor bulk CSV",
        "url": "https://www.tdlr.texas.gov/dbproduction2/Lteecele.csv",
        "fetched_at": "2026-05-16T04:51:42.671073Z",
        "fields": [
          "legal_name",
          "license_number",
          "license_type",
          "license_holder_name",
          "address",
          "city",
          "county",
          "state",
          "zip",
          "phone",
          "license_expiration_date"
        ]
      }
    ],
    "verification_notes": "Sourced from TDLR Electrical Contractor active license roster \u2014 real, currently-operating TX Electrical Contractor license. License number used as tenure proxy.",
    "domain_candidates": [
      "bewleyelectric.com",
      "bewleyelectrical.com",
      "bewleyelectricservices.com"
    ],
    "enrichment": {
      "legal_name": "Bewley Electric",
      "enrichment_status": "mid",
      "website": "https://bewleyelectric.com/",
      "owner_name": "Bewley family",
      "team_page_findings": "Live fetch https://bewleyelectric.com/ \u2014 no named team, generic site. Copyright 2025 (active). No second-gen Bewley visible. Generic services page. Could be A/B but no live team-page-with-names fetched.",
      "successor_check_evidence": "Live homepage shows generic copy with no team names. Per protocol \u2014 no live team-page identifies any specific individual = cap at C_watch. (Family ownership confirmed by BBB but no successor evidence.)",
      "successor_check_direction": "disqualifying",
      "tech_stack": {
        "copyright_year": "2025",
        "ev_charger_offered": "no",
        "online_booking": "no"
      },
      "data_sources": [
        {
          "source": "Live homepage fetch",
          "url": "https://bewleyelectric.com/",
          "fetched_at": "2026-05-15"
        }
      ]
    },
    "enrichment_status": "mid"
  },
  {
    "legal_name": "Parish Electric Co Of Fort Worth, Inc",
    "dba_name": null,
    "address": "5725 Hart Street",
    "city": "Fort Worth",
    "county": "Tarrant",
    "state": "TX",
    "zip": "76112",
    "phone": "8174512931",
    "website": null,
    "naics_code": "238210",
    "license_number": "17470",
    "license_type": "Electrical Contractor",
    "license_subtype": "EC",
    "license_status": "Active",
    "license_holder_name": "Parish Electric Co Of Fort Worth, Inc",
    "license_expiration_date": "07/23/2026",
    "license_issue_year_estimate": 2004,
    "data_sources": [
      {
        "source": "TDLR Electrical Contractor bulk CSV",
        "url": "https://www.tdlr.texas.gov/dbproduction2/Lteecele.csv",
        "fetched_at": "2026-05-16T04:51:42.671075Z",
        "fields": [
          "legal_name",
          "license_number",
          "license_type",
          "license_holder_name",
          "address",
          "city",
          "county",
          "state",
          "zip",
          "phone",
          "license_expiration_date"
        ]
      }
    ],
    "verification_notes": "Sourced from TDLR Electrical Contractor active license roster \u2014 real, currently-operating TX Electrical Contractor license. License number used as tenure proxy.",
    "domain_candidates": [
      "parishfortworthelectric.com",
      "parishfortworthelectrical.com",
      "parishfortworthelectricservices.com",
      "parishelectriccooffortworth.com"
    ],
    "enrichment_status": "spine_only",
    "enrichment": null
  },
  {
    "legal_name": "Colvin Electric, Inc",
    "dba_name": null,
    "address": "3901 Kelly Lane",
    "city": "Pflugerville",
    "county": "Travis",
    "state": "TX",
    "zip": "78660",
    "phone": "5123882271",
    "website": null,
    "naics_code": "238210",
    "license_number": "17495",
    "license_type": "Electrical Contractor",
    "license_subtype": "EC",
    "license_status": "Active",
    "license_holder_name": "Colvin Electric, Inc",
    "license_expiration_date": "07/23/2026",
    "license_issue_year_estimate": 2004,
    "data_sources": [
      {
        "source": "TDLR Electrical Contractor bulk CSV",
        "url": "https://www.tdlr.texas.gov/dbproduction2/Lteecele.csv",
        "fetched_at": "2026-05-16T04:51:42.671077Z",
        "fields": [
          "legal_name",
          "license_number",
          "license_type",
          "license_holder_name",
          "address",
          "city",
          "county",
          "state",
          "zip",
          "phone",
          "license_expiration_date"
        ]
      }
    ],
    "verification_notes": "Sourced from TDLR Electrical Contractor active license roster \u2014 real, currently-operating TX Electrical Contractor license. License number used as tenure proxy.",
    "domain_candidates": [
      "colvinelectric.com",
      "colvinelectrical.com",
      "colvinelectricservices.com"
    ],
    "enrichment": {
      "legal_name": "Colvin Electric, Inc",
      "enrichment_status": "mid",
      "website": "https://colvinelectric.com/",
      "owner_name": "Colvin family",
      "owner_tenure_years": 44,
      "years_in_business": 44,
      "entity_founded": 1982,
      "employee_count_estimate": 25,
      "service_types": [
        "residential",
        "commercial",
        "generators",
        "smart homes",
        "EV chargers"
      ],
      "team_page_findings": "Per company about: 5+ Master Electricians on staff. Family-owned. Multiple internal succession candidates.",
      "successor_check_evidence": "5+ Master Electricians on staff = multiple internal successor candidates. Per protocol, this is internal-buy-in territory, not off-market acquire-self.",
      "successor_check_direction": "negative",
      "data_sources": [
        {
          "source": "TDLR EC bulk CSV",
          "url": "https://www.tdlr.texas.gov/dbproduction2/Lteecele.csv",
          "fetched_at": "2026-05-15"
        },
        {
          "source": "Company about page (search excerpt)",
          "url": "https://colvinelectric.com/",
          "fetched_at": "2026-05-15"
        }
      ]
    },
    "enrichment_status": "mid"
  },
  {
    "legal_name": "Hawk Electric Llc",
    "dba_name": null,
    "address": "10315 Rustic Vlg",
    "city": "San Antonio",
    "county": "Bexar",
    "state": "TX",
    "zip": "78245",
    "phone": "5122280049",
    "website": null,
    "naics_code": "238210",
    "license_number": "17521",
    "license_type": "Electrical Contractor",
    "license_subtype": "EC",
    "license_status": "Active",
    "license_holder_name": "Hawk Electric Llc",
    "license_expiration_date": "07/19/2025",
    "license_issue_year_estimate": 2004,
    "data_sources": [
      {
        "source": "TDLR Electrical Contractor bulk CSV",
        "url": "https://www.tdlr.texas.gov/dbproduction2/Lteecele.csv",
        "fetched_at": "2026-05-16T04:51:42.671080Z",
        "fields": [
          "legal_name",
          "license_number",
          "license_type",
          "license_holder_name",
          "address",
          "city",
          "county",
          "state",
          "zip",
          "phone",
          "license_expiration_date"
        ]
      }
    ],
    "verification_notes": "Sourced from TDLR Electrical Contractor active license roster \u2014 real, currently-operating TX Electrical Contractor license. License number used as tenure proxy.",
    "domain_candidates": [
      "hawkelectric.com",
      "hawkelectrical.com",
      "hawkelectricservices.com"
    ],
    "enrichment_status": "spine_only",
    "enrichment": null
  },
  {
    "legal_name": "Klecka Electric Co Inc",
    "dba_name": null,
    "address": "12107 Colwick St",
    "city": "San Antonio",
    "county": "Bexar",
    "state": "TX",
    "zip": "78216",
    "phone": "2103490123",
    "website": null,
    "naics_code": "238210",
    "license_number": "17526",
    "license_type": "Electrical Contractor",
    "license_subtype": "EC",
    "license_status": "Active",
    "license_holder_name": "Klecka Electric Co Inc",
    "license_expiration_date": "07/26/2026",
    "license_issue_year_estimate": 2004,
    "data_sources": [
      {
        "source": "TDLR Electrical Contractor bulk CSV",
        "url": "https://www.tdlr.texas.gov/dbproduction2/Lteecele.csv",
        "fetched_at": "2026-05-16T04:51:42.671082Z",
        "fields": [
          "legal_name",
          "license_number",
          "license_type",
          "license_holder_name",
          "address",
          "city",
          "county",
          "state",
          "zip",
          "phone",
          "license_expiration_date"
        ]
      }
    ],
    "verification_notes": "Sourced from TDLR Electrical Contractor active license roster \u2014 real, currently-operating TX Electrical Contractor license. License number used as tenure proxy.",
    "domain_candidates": [
      "kleckaelectric.com",
      "kleckaelectrical.com",
      "kleckaelectricservices.com",
      "kleckaelectricco.com"
    ],
    "enrichment_status": "spine_only",
    "enrichment": null
  },
  {
    "legal_name": "System Electric Co. Dba Mcbride Electric",
    "dba_name": null,
    "address": "3301 E Plano Parkway, Suite 150",
    "city": "Plano",
    "county": "Collin",
    "state": "TX",
    "zip": "75074",
    "phone": "4694530997",
    "website": null,
    "naics_code": "238210",
    "license_number": "17550",
    "license_type": "Electrical Contractor",
    "license_subtype": "EC",
    "license_status": "Active",
    "license_holder_name": "System Electric Co. Dba Mcbride Electric",
    "license_expiration_date": "07/26/2026",
    "license_issue_year_estimate": 2004,
    "data_sources": [
      {
        "source": "TDLR Electrical Contractor bulk CSV",
        "url": "https://www.tdlr.texas.gov/dbproduction2/Lteecele.csv",
        "fetched_at": "2026-05-16T04:51:42.671084Z",
        "fields": [
          "legal_name",
          "license_number",
          "license_type",
          "license_holder_name",
          "address",
          "city",
          "county",
          "state",
          "zip",
          "phone",
          "license_expiration_date"
        ]
      }
    ],
    "verification_notes": "Sourced from TDLR Electrical Contractor active license roster \u2014 real, currently-operating TX Electrical Contractor license. License number used as tenure proxy.",
    "domain_candidates": [
      "systemdbamcbrideelectric.com",
      "systemdbamcbrideelectrical.com",
      "systemdbamcbrideelectricservices.com",
      "systemelectriccodbamcbrideelectric.com"
    ],
    "enrichment": {
      "legal_name": "System Electric Co. Dba Mcbride Electric",
      "enrichment_status": "mid",
      "website": "https://www.mcbrideelectric.com/",
      "owner_name": "System Electric Co. (parent)",
      "owner_tenure_years": 65,
      "years_in_business": 65,
      "entity_founded": 1961,
      "service_types": [
        "national multi-branch chain"
      ],
      "exclude_reason": "platform_multi_branch_chain_already_rolled_up",
      "team_page_findings": "Per company materials: 'nation's leading specialized electrical and information transport contractor', 11 regional branches, serves 50%+ Fortune 500. Already platform-scale / rolled up.",
      "successor_check_direction": "negative",
      "data_sources": [
        {
          "source": "TDLR EC bulk CSV",
          "url": "https://www.tdlr.texas.gov/dbproduction2/Lteecele.csv",
          "fetched_at": "2026-05-15"
        }
      ]
    },
    "enrichment_status": "mid"
  },
  {
    "legal_name": "Wheco Electric, Inc",
    "dba_name": null,
    "address": "8501 Jacksboro Highway",
    "city": "Lakeside",
    "county": "Tarrant",
    "state": "TX",
    "zip": "76135",
    "phone": "8172446660",
    "website": null,
    "naics_code": "238210",
    "license_number": "17595",
    "license_type": "Electrical Contractor",
    "license_subtype": "EC",
    "license_status": "Active",
    "license_holder_name": "Wheco Electric, Inc",
    "license_expiration_date": "07/26/2026",
    "license_issue_year_estimate": 2004,
    "data_sources": [
      {
        "source": "TDLR Electrical Contractor bulk CSV",
        "url": "https://www.tdlr.texas.gov/dbproduction2/Lteecele.csv",
        "fetched_at": "2026-05-16T04:51:42.671087Z",
        "fields": [
          "legal_name",
          "license_number",
          "license_type",
          "license_holder_name",
          "address",
          "city",
          "county",
          "state",
          "zip",
          "phone",
          "license_expiration_date"
        ]
      }
    ],
    "verification_notes": "Sourced from TDLR Electrical Contractor active license roster \u2014 real, currently-operating TX Electrical Contractor license. License number used as tenure proxy.",
    "domain_candidates": [
      "whecoelectric.com",
      "whecoelectrical.com",
      "whecoelectricservices.com"
    ],
    "enrichment_status": "spine_only",
    "enrichment": null
  },
  {
    "legal_name": "Ari-Tex Electric, Llc",
    "dba_name": null,
    "address": "1010 S Greenville Avenue",
    "city": "Allen",
    "county": "Collin",
    "state": "TX",
    "zip": "75002",
    "phone": "9727279902",
    "website": null,
    "naics_code": "238210",
    "license_number": "17608",
    "license_type": "Electrical Contractor",
    "license_subtype": "EC",
    "license_status": "Active",
    "license_holder_name": "Ari-Tex Electric, Llc",
    "license_expiration_date": "07/26/2026",
    "license_issue_year_estimate": 2004,
    "data_sources": [
      {
        "source": "TDLR Electrical Contractor bulk CSV",
        "url": "https://www.tdlr.texas.gov/dbproduction2/Lteecele.csv",
        "fetched_at": "2026-05-16T04:51:42.671089Z",
        "fields": [
          "legal_name",
          "license_number",
          "license_type",
          "license_holder_name",
          "address",
          "city",
          "county",
          "state",
          "zip",
          "phone",
          "license_expiration_date"
        ]
      }
    ],
    "verification_notes": "Sourced from TDLR Electrical Contractor active license roster \u2014 real, currently-operating TX Electrical Contractor license. License number used as tenure proxy.",
    "domain_candidates": [
      "aritexelectric.com",
      "aritexelectrical.com",
      "aritexelectricservices.com"
    ],
    "enrichment_status": "spine_only",
    "enrichment": null
  },
  {
    "legal_name": "Tesla Electric Inc",
    "dba_name": null,
    "address": "11222 Applewood Drive",
    "city": "Austin",
    "county": "Travis",
    "state": "TX",
    "zip": "78758",
    "phone": "5125474008",
    "website": null,
    "naics_code": "238210",
    "license_number": "17614",
    "license_type": "Electrical Contractor",
    "license_subtype": "EC",
    "license_status": "Active",
    "license_holder_name": "Tesla Electric Inc",
    "license_expiration_date": "07/26/2026",
    "license_issue_year_estimate": 2004,
    "data_sources": [
      {
        "source": "TDLR Electrical Contractor bulk CSV",
        "url": "https://www.tdlr.texas.gov/dbproduction2/Lteecele.csv",
        "fetched_at": "2026-05-16T04:51:42.671091Z",
        "fields": [
          "legal_name",
          "license_number",
          "license_type",
          "license_holder_name",
          "address",
          "city",
          "county",
          "state",
          "zip",
          "phone",
          "license_expiration_date"
        ]
      }
    ],
    "verification_notes": "Sourced from TDLR Electrical Contractor active license roster \u2014 real, currently-operating TX Electrical Contractor license. License number used as tenure proxy.",
    "domain_candidates": [
      "teslaelectric.com",
      "teslaelectrical.com",
      "teslaelectricservices.com"
    ],
    "enrichment": {
      "legal_name": "Tesla Electric Inc",
      "enrichment_status": "mid",
      "website": "https://teslaelectricinc.com/",
      "owner_name": "Adrian Newcomb",
      "exclude_reason": "yelp_listed_as_closed_may_2024",
      "successor_check_direction": "disqualifying",
      "data_sources": [
        {
          "source": "Yelp",
          "url": "https://www.yelp.com/biz/tesla-electric-austin",
          "fetched_at": "2026-05-15"
        }
      ]
    },
    "enrichment_status": "mid"
  },
  {
    "legal_name": "Simms Electrical Services Inc",
    "dba_name": null,
    "address": "404 San Remo Blvd",
    "city": "Lakeway",
    "county": "Travis",
    "state": "TX",
    "zip": "78734",
    "phone": "5127665399",
    "website": null,
    "naics_code": "238210",
    "license_number": "17701",
    "license_type": "Electrical Contractor",
    "license_subtype": "EC",
    "license_status": "Active",
    "license_holder_name": "Simms Electrical Services Inc",
    "license_expiration_date": "07/26/2026",
    "license_issue_year_estimate": 2004,
    "data_sources": [
      {
        "source": "TDLR Electrical Contractor bulk CSV",
        "url": "https://www.tdlr.texas.gov/dbproduction2/Lteecele.csv",
        "fetched_at": "2026-05-16T04:51:42.671094Z",
        "fields": [
          "legal_name",
          "license_number",
          "license_type",
          "license_holder_name",
          "address",
          "city",
          "county",
          "state",
          "zip",
          "phone",
          "license_expiration_date"
        ]
      }
    ],
    "verification_notes": "Sourced from TDLR Electrical Contractor active license roster \u2014 real, currently-operating TX Electrical Contractor license. License number used as tenure proxy.",
    "domain_candidates": [
      "simmselectric.com",
      "simmselectrical.com",
      "simmselectricservices.com",
      "simmselectricalservices.com"
    ],
    "enrichment_status": "spine_only",
    "enrichment": null
  },
  {
    "legal_name": "Molitor Electric Inc",
    "dba_name": null,
    "address": "915 Beaver Trl Unit B",
    "city": "Austin",
    "county": "Travis",
    "state": "TX",
    "zip": "78746",
    "phone": "5126596410",
    "website": null,
    "naics_code": "238210",
    "license_number": "17722",
    "license_type": "Electrical Contractor",
    "license_subtype": "EC",
    "license_status": "Active",
    "license_holder_name": "Molitor Electric Inc",
    "license_expiration_date": "08/31/2026",
    "license_issue_year_estimate": 2004,
    "data_sources": [
      {
        "source": "TDLR Electrical Contractor bulk CSV",
        "url": "https://www.tdlr.texas.gov/dbproduction2/Lteecele.csv",
        "fetched_at": "2026-05-16T04:51:42.671096Z",
        "fields": [
          "legal_name",
          "license_number",
          "license_type",
          "license_holder_name",
          "address",
          "city",
          "county",
          "state",
          "zip",
          "phone",
          "license_expiration_date"
        ]
      }
    ],
    "verification_notes": "Sourced from TDLR Electrical Contractor active license roster \u2014 real, currently-operating TX Electrical Contractor license. License number used as tenure proxy.",
    "domain_candidates": [
      "molitorelectric.com",
      "molitorelectrical.com",
      "molitorelectricservices.com"
    ],
    "enrichment_status": "spine_only",
    "enrichment": null
  },
  {
    "legal_name": "Premier Electrical",
    "dba_name": null,
    "address": "301 Silver Creek Dr",
    "city": "Leander",
    "county": "Williamson",
    "state": "TX",
    "zip": "78641",
    "phone": "5122598000",
    "website": null,
    "naics_code": "238210",
    "license_number": "17732",
    "license_type": "Electrical Contractor",
    "license_subtype": "EC",
    "license_status": "Active",
    "license_holder_name": "Premier Electrical",
    "license_expiration_date": "07/26/2026",
    "license_issue_year_estimate": 2004,
    "data_sources": [
      {
        "source": "TDLR Electrical Contractor bulk CSV",
        "url": "https://www.tdlr.texas.gov/dbproduction2/Lteecele.csv",
        "fetched_at": "2026-05-16T04:51:42.671098Z",
        "fields": [
          "legal_name",
          "license_number",
          "license_type",
          "license_holder_name",
          "address",
          "city",
          "county",
          "state",
          "zip",
          "phone",
          "license_expiration_date"
        ]
      }
    ],
    "verification_notes": "Sourced from TDLR Electrical Contractor active license roster \u2014 real, currently-operating TX Electrical Contractor license. License number used as tenure proxy.",
    "domain_candidates": [
      "premierelectric.com",
      "premierelectrical.com",
      "premierelectricservices.com"
    ],
    "enrichment_status": "spine_only",
    "enrichment": null
  },
  {
    "legal_name": "Stoever-Parker Electric, Inc",
    "dba_name": null,
    "address": "1441 Interstate 45 North",
    "city": "Conroe",
    "county": "Montgomery",
    "state": "TX",
    "zip": "77304",
    "phone": "7138699024",
    "website": null,
    "naics_code": "238210",
    "license_number": "17736",
    "license_type": "Electrical Contractor",
    "license_subtype": "EC",
    "license_status": "Active",
    "license_holder_name": "Stoever-Parker Electric, Inc",
    "license_expiration_date": "07/26/2025",
    "license_issue_year_estimate": 2004,
    "data_sources": [
      {
        "source": "TDLR Electrical Contractor bulk CSV",
        "url": "https://www.tdlr.texas.gov/dbproduction2/Lteecele.csv",
        "fetched_at": "2026-05-16T04:51:42.671101Z",
        "fields": [
          "legal_name",
          "license_number",
          "license_type",
          "license_holder_name",
          "address",
          "city",
          "county",
          "state",
          "zip",
          "phone",
          "license_expiration_date"
        ]
      }
    ],
    "verification_notes": "Sourced from TDLR Electrical Contractor active license roster \u2014 real, currently-operating TX Electrical Contractor license. License number used as tenure proxy.",
    "domain_candidates": [
      "stoeverparkerelectric.com",
      "stoeverparkerelectrical.com",
      "stoeverparkerelectricservices.com"
    ],
    "enrichment": {
      "legal_name": "Stoever-Parker Electric, Inc",
      "enrichment_status": "mid",
      "website": "https://spehouston.com/home",
      "owner_name": "Stoever + Parker families",
      "owner_tenure_years": 47,
      "years_in_business": 47,
      "entity_founded": 1979,
      "service_types": [
        "commercial only",
        "medical",
        "educational"
      ],
      "exclude_reason": "commercial_only_not_residential",
      "team_page_findings": "Per company materials: 'commercial electrical contracting services since 1979', specializing in medical and educational institutions. Not residential service.",
      "successor_check_direction": "negative",
      "data_sources": [
        {
          "source": "TDLR EC bulk CSV",
          "url": "https://www.tdlr.texas.gov/dbproduction2/Lteecele.csv",
          "fetched_at": "2026-05-15"
        }
      ]
    },
    "enrichment_status": "mid"
  },
  {
    "legal_name": "Denton Electric Inc",
    "dba_name": null,
    "address": "4205 Mesa Drive",
    "city": "Denton",
    "county": "Denton",
    "state": "TX",
    "zip": "76207",
    "phone": "9403871312",
    "website": null,
    "naics_code": "238210",
    "license_number": "17768",
    "license_type": "Electrical Contractor",
    "license_subtype": "EC",
    "license_status": "Active",
    "license_holder_name": "Denton Electric Inc",
    "license_expiration_date": "08/25/2026",
    "license_issue_year_estimate": 2004,
    "data_sources": [
      {
        "source": "TDLR Electrical Contractor bulk CSV",
        "url": "https://www.tdlr.texas.gov/dbproduction2/Lteecele.csv",
        "fetched_at": "2026-05-16T04:51:42.671103Z",
        "fields": [
          "legal_name",
          "license_number",
          "license_type",
          "license_holder_name",
          "address",
          "city",
          "county",
          "state",
          "zip",
          "phone",
          "license_expiration_date"
        ]
      }
    ],
    "verification_notes": "Sourced from TDLR Electrical Contractor active license roster \u2014 real, currently-operating TX Electrical Contractor license. License number used as tenure proxy.",
    "domain_candidates": [
      "dentonelectric.com",
      "dentonelectrical.com",
      "dentonelectricservices.com"
    ],
    "enrichment": {
      "legal_name": "Denton Electric Inc",
      "enrichment_status": "mid",
      "website": "https://www.dentonelectricinc.com/",
      "owner_name": "Walding family (Ben, Josh, Chris \u2014 3rd generation; founded 1922)",
      "owner_age_estimate": null,
      "owner_age_source": "linkedin_proxy",
      "owner_tenure_years": 25,
      "years_in_business": 104,
      "entity_founded": 1922,
      "employee_count_estimate": 30,
      "service_types": [
        "residential installation & service",
        "commercial"
      ],
      "tech_stack": {
        "online_booking": "not_visible",
        "ev_charger_offered": "not_visible",
        "generator_install_offered": "not_visible"
      },
      "team_page_findings": "Per about page: 3rd-generation Walding owners (Ben, Josh, Chris). 4 Master Electricians on staff. Clear internal succession.",
      "successor_check_evidence": "3rd-gen Walding family + 4 Master Electricians on staff. Multiple internal successors. NOT off-market target.",
      "successor_check_direction": "negative",
      "data_sources": [
        {
          "source": "TDLR EC bulk CSV",
          "url": "https://www.tdlr.texas.gov/dbproduction2/Lteecele.csv",
          "fetched_at": "2026-05-15"
        },
        {
          "source": "About page",
          "url": "https://www.dentonelectricinc.com/about-denton-electric-inc/",
          "fetched_at": "2026-05-15"
        }
      ]
    },
    "enrichment_status": "mid"
  },
  {
    "legal_name": "Advanced Electric Company",
    "dba_name": null,
    "address": "4251 Fm 2181 Ste 230",
    "city": "Corinth",
    "county": "Denton",
    "state": "TX",
    "zip": "76210",
    "phone": "2148695403",
    "website": null,
    "naics_code": "238210",
    "license_number": "17789",
    "license_type": "Electrical Contractor",
    "license_subtype": "EC",
    "license_status": "Active",
    "license_holder_name": "Advanced Electric Company",
    "license_expiration_date": "12/13/2026",
    "license_issue_year_estimate": 2004,
    "data_sources": [
      {
        "source": "TDLR Electrical Contractor bulk CSV",
        "url": "https://www.tdlr.texas.gov/dbproduction2/Lteecele.csv",
        "fetched_at": "2026-05-16T04:51:42.671105Z",
        "fields": [
          "legal_name",
          "license_number",
          "license_type",
          "license_holder_name",
          "address",
          "city",
          "county",
          "state",
          "zip",
          "phone",
          "license_expiration_date"
        ]
      }
    ],
    "verification_notes": "Sourced from TDLR Electrical Contractor active license roster \u2014 real, currently-operating TX Electrical Contractor license. License number used as tenure proxy.",
    "domain_candidates": [
      "advancedelectric.com",
      "advancedelectrical.com",
      "advancedelectricservices.com"
    ],
    "enrichment": {
      "legal_name": "Advanced Electric Company",
      "enrichment_status": "mid",
      "website": null,
      "successor_check_evidence": "No live team page found. Yelp/Procore only. Per protocol cap at C_watch.",
      "successor_check_direction": "disqualifying",
      "data_sources": [
        {
          "source": "Yelp",
          "url": "https://www.yelp.com/biz/advanced-electric-corinth",
          "fetched_at": "2026-05-15"
        }
      ]
    },
    "enrichment_status": "mid"
  },
  {
    "legal_name": "Stence Electric, Inc",
    "dba_name": null,
    "address": "1001 W 2Nd St",
    "city": "Taylor",
    "county": "Williamson",
    "state": "TX",
    "zip": "76574",
    "phone": "5123657785",
    "website": null,
    "naics_code": "238210",
    "license_number": "17831",
    "license_type": "Electrical Contractor",
    "license_subtype": "EC",
    "license_status": "Active",
    "license_holder_name": "Stence Electric, Inc",
    "license_expiration_date": "12/04/2026",
    "license_issue_year_estimate": 2004,
    "data_sources": [
      {
        "source": "TDLR Electrical Contractor bulk CSV",
        "url": "https://www.tdlr.texas.gov/dbproduction2/Lteecele.csv",
        "fetched_at": "2026-05-16T04:51:42.671109Z",
        "fields": [
          "legal_name",
          "license_number",
          "license_type",
          "license_holder_name",
          "address",
          "city",
          "county",
          "state",
          "zip",
          "phone",
          "license_expiration_date"
        ]
      }
    ],
    "verification_notes": "Sourced from TDLR Electrical Contractor active license roster \u2014 real, currently-operating TX Electrical Contractor license. License number used as tenure proxy.",
    "domain_candidates": [
      "stenceelectric.com",
      "stenceelectrical.com",
      "stenceelectricservices.com"
    ],
    "enrichment_status": "spine_only",
    "enrichment": null
  },
  {
    "legal_name": "Owens Electric",
    "dba_name": null,
    "address": "8500 Holder Road",
    "city": "Justin",
    "county": "Denton",
    "state": "TX",
    "zip": "76247",
    "phone": "9405369015",
    "website": null,
    "naics_code": "238210",
    "license_number": "17839",
    "license_type": "Electrical Contractor",
    "license_subtype": "EC",
    "license_status": "Active",
    "license_holder_name": "Owens Electric",
    "license_expiration_date": "07/26/2026",
    "license_issue_year_estimate": 2004,
    "data_sources": [
      {
        "source": "TDLR Electrical Contractor bulk CSV",
        "url": "https://www.tdlr.texas.gov/dbproduction2/Lteecele.csv",
        "fetched_at": "2026-05-16T04:51:42.671111Z",
        "fields": [
          "legal_name",
          "license_number",
          "license_type",
          "license_holder_name",
          "address",
          "city",
          "county",
          "state",
          "zip",
          "phone",
          "license_expiration_date"
        ]
      }
    ],
    "verification_notes": "Sourced from TDLR Electrical Contractor active license roster \u2014 real, currently-operating TX Electrical Contractor license. License number used as tenure proxy.",
    "domain_candidates": [
      "owenselectric.com",
      "owenselectrical.com",
      "owenselectricservices.com"
    ],
    "enrichment_status": "spine_only",
    "enrichment": null
  },
  {
    "legal_name": "Wcs Electric, Inc",
    "dba_name": null,
    "address": "502 Business Highway 78 South",
    "city": "Blue Ridge",
    "county": "Collin",
    "state": "TX",
    "zip": "75424",
    "phone": "4695760280",
    "website": null,
    "naics_code": "238210",
    "license_number": "17887",
    "license_type": "Electrical Contractor",
    "license_subtype": "EC",
    "license_status": "Active",
    "license_holder_name": "Wcs Electric, Inc",
    "license_expiration_date": "07/28/2026",
    "license_issue_year_estimate": 2004,
    "data_sources": [
      {
        "source": "TDLR Electrical Contractor bulk CSV",
        "url": "https://www.tdlr.texas.gov/dbproduction2/Lteecele.csv",
        "fetched_at": "2026-05-16T04:51:42.671113Z",
        "fields": [
          "legal_name",
          "license_number",
          "license_type",
          "license_holder_name",
          "address",
          "city",
          "county",
          "state",
          "zip",
          "phone",
          "license_expiration_date"
        ]
      }
    ],
    "verification_notes": "Sourced from TDLR Electrical Contractor active license roster \u2014 real, currently-operating TX Electrical Contractor license. License number used as tenure proxy.",
    "domain_candidates": [
      "wcselectric.com",
      "wcselectrical.com",
      "wcselectricservices.com"
    ],
    "enrichment_status": "spine_only",
    "enrichment": null
  },
  {
    "legal_name": "Sorensen Electric, Inc",
    "dba_name": null,
    "address": "1770 Millard Dr Suite D",
    "city": "Plano",
    "county": "Collin",
    "state": "TX",
    "zip": "75074",
    "phone": "9725789395",
    "website": null,
    "naics_code": "238210",
    "license_number": "17929",
    "license_type": "Electrical Contractor",
    "license_subtype": "EC",
    "license_status": "Active",
    "license_holder_name": "Sorensen Electric, Inc",
    "license_expiration_date": "07/30/2026",
    "license_issue_year_estimate": 2004,
    "data_sources": [
      {
        "source": "TDLR Electrical Contractor bulk CSV",
        "url": "https://www.tdlr.texas.gov/dbproduction2/Lteecele.csv",
        "fetched_at": "2026-05-16T04:51:42.671116Z",
        "fields": [
          "legal_name",
          "license_number",
          "license_type",
          "license_holder_name",
          "address",
          "city",
          "county",
          "state",
          "zip",
          "phone",
          "license_expiration_date"
        ]
      }
    ],
    "verification_notes": "Sourced from TDLR Electrical Contractor active license roster \u2014 real, currently-operating TX Electrical Contractor license. License number used as tenure proxy.",
    "domain_candidates": [
      "sorensenelectric.com",
      "sorensenelectrical.com",
      "sorensenelectricservices.com"
    ],
    "enrichment_status": "spine_only",
    "enrichment": null
  },
  {
    "legal_name": "Heier Electric",
    "dba_name": null,
    "address": "1204 Rice Ave",
    "city": "Cedar Park",
    "county": "Williamson",
    "state": "TX",
    "zip": "78613",
    "phone": "5126578851",
    "website": null,
    "naics_code": "238210",
    "license_number": "18014",
    "license_type": "Electrical Contractor",
    "license_subtype": "EC",
    "license_status": "Active",
    "license_holder_name": "Heier Electric",
    "license_expiration_date": "08/12/2025",
    "license_issue_year_estimate": 2006,
    "data_sources": [
      {
        "source": "TDLR Electrical Contractor bulk CSV",
        "url": "https://www.tdlr.texas.gov/dbproduction2/Lteecele.csv",
        "fetched_at": "2026-05-16T04:51:42.671118Z",
        "fields": [
          "legal_name",
          "license_number",
          "license_type",
          "license_holder_name",
          "address",
          "city",
          "county",
          "state",
          "zip",
          "phone",
          "license_expiration_date"
        ]
      }
    ],
    "verification_notes": "Sourced from TDLR Electrical Contractor active license roster \u2014 real, currently-operating TX Electrical Contractor license. License number used as tenure proxy.",
    "domain_candidates": [
      "heierelectric.com",
      "heierelectrical.com",
      "heierelectricservices.com"
    ],
    "enrichment_status": "spine_only",
    "enrichment": null
  },
  {
    "legal_name": "Custom Electric Design Inc",
    "dba_name": null,
    "address": "3515 Stratford Manor",
    "city": "Sugarland",
    "county": "Fort Bend",
    "state": "TX",
    "zip": "77498",
    "phone": "2817235431",
    "website": null,
    "naics_code": "238210",
    "license_number": "18149",
    "license_type": "Electrical Contractor",
    "license_subtype": "EC",
    "license_status": "Active",
    "license_holder_name": "Custom Electric Design Inc",
    "license_expiration_date": "08/06/2026",
    "license_issue_year_estimate": 2006,
    "data_sources": [
      {
        "source": "TDLR Electrical Contractor bulk CSV",
        "url": "https://www.tdlr.texas.gov/dbproduction2/Lteecele.csv",
        "fetched_at": "2026-05-16T04:51:42.671120Z",
        "fields": [
          "legal_name",
          "license_number",
          "license_type",
          "license_holder_name",
          "address",
          "city",
          "county",
          "state",
          "zip",
          "phone",
          "license_expiration_date"
        ]
      }
    ],
    "verification_notes": "Sourced from TDLR Electrical Contractor active license roster \u2014 real, currently-operating TX Electrical Contractor license. License number used as tenure proxy.",
    "domain_candidates": [
      "customdesignelectric.com",
      "customdesignelectrical.com",
      "customdesignelectricservices.com",
      "customelectricdesign.com"
    ],
    "enrichment_status": "spine_only",
    "enrichment": null
  },
  {
    "legal_name": "Watts Electric Inc",
    "dba_name": null,
    "address": "5532 Gemstone Park Rd",
    "city": "Richmond",
    "county": "Fort Bend",
    "state": "TX",
    "zip": "77407",
    "phone": "2818796668",
    "website": null,
    "naics_code": "238210",
    "license_number": "18167",
    "license_type": "Electrical Contractor",
    "license_subtype": "EC",
    "license_status": "Active",
    "license_holder_name": "Watts Electric Inc",
    "license_expiration_date": "08/09/2026",
    "license_issue_year_estimate": 2006,
    "data_sources": [
      {
        "source": "TDLR Electrical Contractor bulk CSV",
        "url": "https://www.tdlr.texas.gov/dbproduction2/Lteecele.csv",
        "fetched_at": "2026-05-16T04:51:42.671123Z",
        "fields": [
          "legal_name",
          "license_number",
          "license_type",
          "license_holder_name",
          "address",
          "city",
          "county",
          "state",
          "zip",
          "phone",
          "license_expiration_date"
        ]
      }
    ],
    "verification_notes": "Sourced from TDLR Electrical Contractor active license roster \u2014 real, currently-operating TX Electrical Contractor license. License number used as tenure proxy.",
    "domain_candidates": [
      "wattselectric.com",
      "wattselectrical.com",
      "wattselectricservices.com"
    ],
    "enrichment_status": "spine_only",
    "enrichment": null
  }
]